README.md
setup.py
se360demo/__init__.py
se360demo.egg-info/PKG-INFO
se360demo.egg-info/SOURCES.txt
se360demo.egg-info/dependency_links.txt
se360demo.egg-info/requires.txt
se360demo.egg-info/top_level.txt
se360demo/data/delivery-time.dxpx
se360demo/data/rain-events.csv
se360demo/data/rsm-cubic.dxpx
se360demo/data/rsm-sim.dxpx
se360demo/data/sin.dxpx
se360demo/data/streamflow-empty.dxpx